Lab2_Filter/fir_filter_parallel.v
// =============================================================================
// Module: fir_filter_parallel
// Description: 25-tap Direct Form FIR Low-Pass Filter, 2x Parallel Speedup
//
// Block processing: 2 input samples per clock -> 2 output samples per clock
// Throughput = 2x compared to fir_filter.v at the same clock rate
//
// Word-length (same as fir_filter.v):
//   Input  x : 16 bits signed [1 Sign + 2 Int + 13 Frac]  b_in   = 13
//   Coeff  h : 17 bits signed [1 Sign + 1 Int + 15 Frac]  b_coef = 15
//   Mult out : 20 bits signed [1 Sign + 2 Int + 17 Frac]  b_mult = 17
//   Add  out : 21 bits signed [1 Sign + 3 Int + 17 Frac]  b_add  = 17
//   Output y : 21 bits signed (same as adder output)
//
// Parallel derivation (shift_reg has TAPS+1 = 26 entries after update):
//   shift_reg[0]  = FilterIn1  (x[2n+1], newest)
//   shift_reg[1]  = FilterIn0  (x[2n])
//   shift_reg[k]  = old shift_reg[k-2], k=2..25
//
//   FilterOut1 = y[2n+1] = SUM h[k] * shift_reg[k],   k=0..24
//   FilterOut0 = y[2n]   = SUM h[k] * shift_reg[k+1], k=0..24
// =============================================================================

module fir_filter_parallel (
    input  wire        clk,
    input  wire        rst_n,
    input  wire signed [15:0] FilterIn0,  // x[2n]   even sample (older)
    input  wire signed [15:0] FilterIn1,  // x[2n+1] odd  sample (newer)
    input  wire        ValidIn,
    output reg  signed [20:0] FilterOut0, // y[2n]
    output reg  signed [20:0] FilterOut1, // y[2n+1]
    output reg         ValidOut
);

parameter TAPS   = 25;
parameter W_IN   = 16;
parameter W_COEF = 17;
parameter W_MULT = 20;
parameter W_ADD  = 21;
parameter F_IN   = 13;
parameter F_COEF = 15;
parameter F_MULT = 17;
parameter F_ADD  = 17;

localparam MULT_DISCARD = F_IN + F_COEF - F_MULT;  // 13+15-17 = 11
localparam W_MULT_FULL  = W_IN + W_COEF;            // 16+17    = 33

// =============================================================================
// Coefficient ROM [1S+1I+15F, 17-bit signed]
// =============================================================================
reg signed [W_COEF-1:0] h_coef [0:TAPS-1];

initial $readmemh("C:/Project/DSP in VLSI/Lab2_Filter/matlab/h_coef.dat", h_coef);

// =============================================================================
// Shift Register: TAPS+1 = 26 entries
// shift_reg[0]  = FilterIn1 (newest)
// shift_reg[1]  = FilterIn0
// shift_reg[k]  = old shift_reg[k-2], k=2..25
// =============================================================================
reg signed [W_IN-1:0] shift_reg [0:TAPS];  // 0..25
reg valid_pipe;

integer si;
always @(posedge clk) begin
    if (!rst_n) begin
        for (si = 0; si <= TAPS; si = si + 1)
            shift_reg[si] <= 0;
        valid_pipe <= 0;
    end else begin
        valid_pipe <= ValidIn;
        if (ValidIn) begin
            shift_reg[0] <= FilterIn1;
            shift_reg[1] <= FilterIn0;
            for (si = 2; si <= TAPS; si = si + 1)
                shift_reg[si] <= shift_reg[si-2];
        end
    end
end

// =============================================================================
// Stage 1: Two sets of 25 multipliers + truncation
// Out1 uses shift_reg[0..24], Out0 uses shift_reg[1..25]
// full = 33 bits, discard 11 LSBs -> keep [32:11] = 20 bits
// =============================================================================
wire signed [W_MULT_FULL-1:0] mult_full1  [0:TAPS-1];
wire signed [W_MULT_FULL-1:0] mult_full0  [0:TAPS-1];
wire signed [W_MULT-1:0]      mult_trunc1 [0:TAPS-1];
wire signed [W_MULT-1:0]      mult_trunc0 [0:TAPS-1];

genvar gi;
generate
    for (gi = 0; gi < TAPS; gi = gi + 1) begin : MULT_STAGE
        assign mult_full1[gi]  = shift_reg[gi]   * h_coef[gi];
        assign mult_full0[gi]  = shift_reg[gi+1] * h_coef[gi];
        assign mult_trunc1[gi] = mult_full1[gi][W_MULT_FULL-1 : MULT_DISCARD];
        assign mult_trunc0[gi] = mult_full0[gi][W_MULT_FULL-1 : MULT_DISCARD];
    end
endgenerate

// =============================================================================
// Stage 2: Two chained accumulators
// Sign-extend mult_trunc (20-bit) to 21-bit, accumulate
// =============================================================================
reg signed [W_ADD-1:0] acc1 [0:TAPS-1];
reg signed [W_ADD-1:0] acc0 [0:TAPS-1];

integer ai;
always @(*) begin
    acc1[0] = {{(W_ADD-W_MULT){mult_trunc1[0][W_MULT-1]}}, mult_trunc1[0]};
    acc0[0] = {{(W_ADD-W_MULT){mult_trunc0[0][W_MULT-1]}}, mult_trunc0[0]};
    for (ai = 1; ai < TAPS; ai = ai + 1) begin
        acc1[ai] = acc1[ai-1] + {{(W_ADD-W_MULT){mult_trunc1[ai][W_MULT-1]}}, mult_trunc1[ai]};
        acc0[ai] = acc0[ai-1] + {{(W_ADD-W_MULT){mult_trunc0[ai][W_MULT-1]}}, mult_trunc0[ai]};
    end
end

// =============================================================================
// Output DFF
// =============================================================================
always @(posedge clk) begin
    if (!rst_n) begin
        FilterOut0 <= 0;
        FilterOut1 <= 0;
        ValidOut   <= 0;
    end else begin
        ValidOut <= valid_pipe;
        if (valid_pipe) begin
            FilterOut0 <= acc0[TAPS-1];
            FilterOut1 <= acc1[TAPS-1];
        end
    end
end

endmodule

Lab2_Filter/fir_filter_parallel_tb.v
// =============================================================================
// Testbench: fir_filter_parallel_tb
// 從外部 x_input.dat 讀取輸入，每 clock 送 2 個樣本
// 輸出寫入 y_parallel_output.dat（格式與 y_output.dat 相同，可直接比對）
//
// 輸入格式：16-bit signed [1S+2I+13F]，x_input.dat 每行 4 位 hex
// 輸出格式：21-bit signed [1S+3I+17F]，每行 signed 整數
//   轉回浮點：y_float = y_integer / 2^17
//
// 驗證：y_parallel_output.dat 應與 y_output.dat 數值完全一致
// =============================================================================

`timescale 1ns / 1ps

module fir_filter_parallel_tb;

parameter CLK_PERIOD  = 10;
parameter N_SAMPLES   = 144;
parameter N_CLK_IN    = N_SAMPLES / 2;  // 72 clocks to send all inputs
parameter F_ADD       = 17;

reg clk, rst_n;
always #(CLK_PERIOD/2) clk = ~clk;

// DUT
reg  signed [15:0] FilterIn0;
reg  signed [15:0] FilterIn1;
reg                ValidIn;
wire signed [20:0] FilterOut0;
wire signed [20:0] FilterOut1;
wire               ValidOut;

fir_filter_parallel dut (
    .clk       (clk),
    .rst_n     (rst_n),
    .FilterIn0 (FilterIn0),
    .FilterIn1 (FilterIn1),
    .ValidIn   (ValidIn),
    .FilterOut0(FilterOut0),
    .FilterOut1(FilterOut1),
    .ValidOut  (ValidOut)
);

// =============================================================================
// 從 x_input.dat 讀取測試向量
// =============================================================================
reg [15:0] test_input [0:N_SAMPLES-1];

initial begin
    $readmemh("C:/Project/DSP in VLSI/Lab2_Filter/matlab/x_input.dat", test_input);
end

// =============================================================================
// 主要 stimulus
// =============================================================================
integer i;
integer out_count;
integer out_file;
real    y_float0, y_float1;

initial begin
    $dumpfile("fir_parallel_sim.vcd");
    $dumpvars(0, fir_filter_parallel_tb);

    clk       = 0;
    rst_n     = 0;
    FilterIn0 = 0;
    FilterIn1 = 0;
    ValidIn   = 0;
    out_count = 0;

    out_file = $fopen("y_parallel_output.dat", "w");

    // Reset 4 cycles
    repeat(4) @(posedge clk);
    #1 rst_n = 1;

    $display("=== FIR Parallel Filter Simulation Start ===");
    $display("Input : 16-bit signed [1S+2I+13F], 2 samples/clock");
    $display("Output: 21-bit signed [1S+3I+17F], 2 outputs/clock, float = int / 2^%0d", F_ADD);
    $display("");

    // 每個 clock 送 2 個樣本：test_input[2i] 和 test_input[2i+1]
    for (i = 0; i < N_CLK_IN; i = i + 1) begin
        @(posedge clk);
        #1;
        FilterIn0 = test_input[2*i];      // x[2n]   even (older)
        FilterIn1 = test_input[2*i + 1];  // x[2n+1] odd  (newer)
        ValidIn   = 1;
    end

    // 關閉輸入，等 pipeline flush（2 cycle latency）
    @(posedge clk); #1;
    FilterIn0 = 0;
    FilterIn1 = 0;
    ValidIn   = 0;
    repeat(5) @(posedge clk);

    $fclose(out_file);
    $display("");
    $display("=== Simulation Done: y_parallel_output.dat saved ===");
    $finish;
end

// =============================================================================
// 輸出監控：每 clock 收 2 個輸出，寫入順序 y[2n] 先、y[2n+1] 後
// =============================================================================
always @(posedge clk) begin
    if (ValidOut) begin
        y_float0 = $itor($signed(FilterOut0)) / (2.0 ** F_ADD);
        y_float1 = $itor($signed(FilterOut1)) / (2.0 ** F_ADD);

        // 寫入輸出檔（y[2n] 先，y[2n+1] 後，與 y_output.dat 順序一致）
        $fdisplay(out_file, "%d", $signed(FilterOut0));
        $fdisplay(out_file, "%d", $signed(FilterOut1));

        // 顯示前 10 筆（即前 20 個 output）
        if (out_count < 10) begin
            $display("[y%3d] int=%10d  float=%9.5f", 2*out_count,   $signed(FilterOut0), y_float0);
            $display("[y%3d] int=%10d  float=%9.5f", 2*out_count+1, $signed(FilterOut1), y_float1);
        end

        // 顯示後 10 筆（即後 20 個 output）
        if (out_count >= N_CLK_IN-10) begin
            $display("[y%3d] int=%10d  float=%9.5f", 2*out_count,   $signed(FilterOut0), y_float0);
            $display("[y%3d] int=%10d  float=%9.5f", 2*out_count+1, $signed(FilterOut1), y_float1);
        end

        out_count = out_count + 1;
    end
end

// Timeout
initial begin
    #100000;
    $display("ERROR: Timeout");
    $finish;
end

endmodule

Lab2_Filter/FIR_FILTER/FIR_FILTER.sim/sim_1/behav/xsim/fir_parallel_sim.vcd
$date
   Wed Mar 25 05:26:07 2026
$end

$version
  2024.1
  $dumpfile ("fir_parallel_sim.vcd") 
$end

$timescale
  1ps
$end

$scope module fir_filter_parallel_tb $end
$var reg 1 ! clk $end
$var reg 1 " rst_n $end
$var reg 16 # FilterIn0 [15:0] $end
$var reg 16 $ FilterIn1 [15:0] $end
$var reg 1 % ValidIn $end
$var wire 21 & FilterOut0 [20:0] $end
$var wire 21 ' FilterOut1 [20:0] $end
$var wire 1 ( ValidOut $end
$var integer 32 ) i [31:0] $end
$var integer 32 * out_count [31:0] $end
$var integer 32 + out_file [31:0] $end
$var real 32 , y_float0 $end
$var real 32 - y_float1 $end
$scope module dut $end
$var wire 1 . clk $end
$var wire 1 / rst_n $end
$var wire 16 0 FilterIn0 [15:0] $end
$var wire 16 1 FilterIn1 [15:0] $end
$var wire 1 2 ValidIn $end
$var reg 21 3 FilterOut0 [20:0] $end
$var reg 21 4 FilterOut1 [20:0] $end
$var reg 1 5 ValidOut $end
$var reg 1 6 valid_pipe $end
$var integer 32 7 si [31:0] $end
$var integer 32 8 ai [31:0] $end
$upscope $end
$upscope $end
$enddefinitions $end

#0
$dumpvars
0!
0"
b0 #
b0 $
0%
bx &
bx '
x(
bx )
b0 *
b11111111111111111011000111100000 +
r0 ,
r0 -
0.
0/
b0 0
b0 1
02
bx 3
bx 4
x5
x6
bx 7
bx 8
$end

#5000
1!
b0 &
b0 '
0(
1.
b0 3
b0 4
05
06
b11010 7
b11001 8

#10000
0!
0.

#15000
1!
1.
b11010 7

#20000
0!
0.

#25000
1!
1.
b11010 7

#30000
0!
0.

#35000
1!
1.
b11010 7

#36000
1"
b0 )
1/

#40000
0!
0.

#45000
1!
1.

#46000
b1110000000000000 #
b1111111001101110 $
1%
b1 )
b1110000000000000 0
b1111111001101110 1
12

#50000
0!
0.

#55000
1!
1.
16
b11010 7
b11001 8

#56000
b1110011011101 #
b1111101101001101 $
b10 )
b1110011011101 0
b1111101101001101 1

#60000
0!
0.

#65000
1!
b100 &
b10110001110100 '
1(
1.
b100 3
b10110001110100 4
15
b11010 7
b11001 8

#66000
b1101100111000001 #
b1111100000111001 $
b11 )
b1101100111000001 0
b1111100000111001 1

#70000
0!
0.

#75000
1!
b101011011011010 &
b100100010110110 '
b1 *
r3.0517578125e-05 ,
r0.086822509765625 -
1.
b101011011011010 3
b100100010110110 4
b11010 7
b11001 8

#76000
b1011010110101 #
b1111010100111000 $
b100 )
b1011010110101 0
b1111010100111000 1

#80000
0!
0.

#85000
1!
b10100101011000 &
b10101010011011 '
b10 *
r0.1696319580078125 ,
r0.1420135498046875 -
1.
b10100101011000 3
b10101010011011 4
b11010 7
b11001 8

#86000
b1101001111000001 #
b1111001001010001 $
b101 )
b1101001111000001 0
b1111001001010001 1

#90000
0!
0.

#95000
1!
b10001111100110 &
b111111110010110100111 '
b11 *
r0.08074951171875 ,
r0.08321380615234375 -
1.
b10001111100110 3
b111111110010110100111 4
b11010 7
b11001 8

#96000
b1000011101010 #
b1110111110001100 $
b110 )
b1000011101010 0
b1110111110001100 1

#100000
0!
0.

#105000
1!
b111111001110110010100 &
b111111000000111111011 '
b100 *
r0.0701141357421875 ,
r-0.05146026611328125 -
1.
b111111001110110010100 3
b111111000000111111011 4
b11010 7
b11001 8

#106000
b1100111000111000 #
b1110110011110000 $
b111 )
b1100111000111000 0
b1110110011110000 1

#110000
0!
0.

#115000
1!
b111110110101110111101 &
b111110010100101011110 '
b101 *
r-0.192230224609375 ,
r-0.2461318969726562 -
1.
b111110110101110111101 3
b111110010100101011110 4
b11010 7
b11001 8

#116000
b101110110011 #
b1110101010000010 $
b1000 )
b101110110011 0
b1110101010000010 1

#120000
0!
0.

#125000
1!
b111101110001110111001 &
b111101100101001000100 '
b110 *
r-0.2895736694335938 ,
r-0.4192047119140625 -
1.
b111101110001110111001 3
b111101100101001000100 4
b11010 7
b11001 8

#126000
b1100100101011111 #
b1110100001001010 $
b1001 )
b1100100101011111 0
b1110100001001010 1

#130000
0!
0.

#135000
1!
b111101010111010011011 &
b111100101100101001111 '
b111 *
r-0.5552291870117188 ,
r-0.604949951171875 -
1.
b111101010111010011011 3
b111100101100101001111 4
b11010 7
b11001 8

#136000
b11101000011 #
b1110011001001100 $
b1010 )
b11101000011 0
b1110011001001100 1

#140000
0!
0.

#145000
1!
b111011110111111110111 &
b111011010001001100011 '
b1000 *
r-0.6589736938476562 ,
r-0.8255691528320312 -
1.
b111011110111111110111 3
b111011010001001100011 4
b11010 7
b11001 8

#146000
b1100010101100100 #
b1110010010001101 $
b1011 )
b1100010101100100 0
b1110010010001101 1

#150000
0!
0.

#155000
1!
b111010100011000101110 &
b111001010101011100000 '
b1001 *
r-1.031318664550781 ,
r-1.182838439941406 -
1.
b111010100011000101110 3
b111001010101011100000 4
b11010 7
b11001 8

#156000
b1111000111 #
b1110001100010010 $
b1100 )
b1111000111 0
b1110001100010010 1

#160000
0!
0.

#165000
1!
b110111111111010101010 &
b110110111100111110110 '
b1010 *
r-1.362930297851562 ,
r-1.666259765625 -
1.
b110111111111010101010 3
b110110111100111110110 4
b11010 7
b11001 8

#166000
b1100001001101111 #
b1110000111011110 $
b1101 )
b1100001001101111 0
b1110000111011110 1

#170000
0!
0.

#175000
1!
b110101111100101000111 &
b110100100111111101111 '
b1011 *
r-2.002609252929688 ,
r-2.261795043945312 -
1.
b110101111100101000111 3
b110100100111111101111 4
b11010 7
b11001 8

#176000
b101100000 #
b1110000011110101 $
b1110 )
b101100000 0
b1110000011110101 1

#180000
0!
0.

#185000
1!
b110011010110001001110 &
b110010110100011100011 '
b1100 *
r-2.513130187988281 ,
r-2.843879699707031 -
1.
b110011010110001001110 3
b110010110100011100011 4
b11010 7
b11001 8

#186000
b1100000010011101 #
b1110000001011000 $
b1111 )
b1100000010011101 0
b1110000001011000 1

#190000
0!
0.

#195000
1!
b110010010100110000111 &
b110001001001000001110 '
b1101 *
r-3.163467407226562 ,
r-3.295143127441406 -
1.
b110010010100110000111 3
b110001001001000001110 4
b11010 7
b11001 8

#196000
b100111 #
b1110000000001001 $
b10000 )
b100111 0
b1110000000001001 1

#200000
0!
0.

#205000
1!
b101111111111100101001 &
b101111100110110000111 '
b1110 *
r-3.418891906738281 ,
r-3.714736938476562 -
1.
b101111111111100101001 3
b101111100110110000111 4
b11010 7
b11001 8

#206000
b1100000000000000 #
b10001 )
b1100000000000000 0

#210000
0!
0.

#215000
1!
b101111010000011110110 &
b101110001110100110101 '
b1111 *
r-4.001640319824219 ,
r-4.098579406738281 -
1.
b101111010000011110110 3
b101110001110100110101 4
b11010 7
b11001 8

#216000
b100111 #
b1110000001011000 $
b10010 )
b100111 0
b1110000001011000 1

#220000
0!
0.

#225000
1!
b101101001111011110000 &
b101101000001011000100 '
b10000 *
r-4.185623168945312 ,
r-4.442955017089844 -
1.
b101101001111011110000 3
b101101000001011000100 4
b11010 7
b11001 8

#226000
b1100000010011101 #
b1110000011110101 $
b10011 )
b1100000010011101 0
b1110000011110101 1

#230000
0!
0.

#235000
1!
b101100110110001110110 &
b101011111111110111010 '
b10001 *
r-4.6895751953125 ,
r-4.744598388671875 -
1.
b101100110110001110110 3
b101011111111110111010 4
b11010 7
b11001 8

#236000
b101100000 #
b1110000111011110 $
b10100 )
b101100000 0
b1110000111011110 1

#240000
0!
0.

#245000
1!
b101011001100100101011 &
b101011001010101011100 '
b10010 *
r-4.788162231445312 ,
r-5.000534057617188 -
1.
b101011001100100101011 3
b101011001010101011100 4
b11010 7
b11001 8

#246000
b1100001001101111 #
b1110001100010010 $
b10101 )
b1100001001101111 0
b1110001100010010 1

#250000
0!
0.

#255000
1!
b101011001011111111001 &
b101010100010010101101 '
b10011 *
r-5.200843811035156 ,
r-5.208282470703125 -
1.
b101011001011111111001 3
b101010100010010101101 4
b11010 7
b11001 8

#256000
b1111000111 #
b1110010010001101 $
b10110 )
b1111000111 0
b1110010010001101 1

#260000
0!
0.

#265000
1!
b101001111100000000011 &
b101010000111001111010 '
b10100 *
r-5.203178405761719 ,
r-5.365867614746094 -
1.
b101001111100000000011 3
b101010000111001111010 4
b11010 7
b11001 8

#266000
b1100010101100100 #
b1110011001001100 $
b10111 )
b1100010101100100 0
b1110011001001100 1

#270000
0!
0.

#275000
1!
b101010010101110110011 &
b101001111001101000000 '
b10101 *
r-5.515602111816406 ,
r-5.471725463867188 -
1.
b101010010101110110011 3
b101001111001101000000 4
b11010 7
b11001 8

#276000
b11101000011 #
b1110100001001010 $
b11000 )
b11101000011 0
b1110100001001010 1

#280000
0!
0.

#285000
1!
b101001100000110100010 &
b10110 *
r-5.414649963378906 ,
r-5.52490234375 -
1.
b101001100000110100010 3
b11010 7
b11001 8

#286000
b1100100101011111 #
b1110101010000010 $
b11001 )
b1100100101011111 0
b1110101010000010 1

#290000
0!
0.

#295000
1!
b101010010101110110011 &
b101010000111001111010 '
b10111 *
r-5.621810913085938 ,
1.
b101010010101110110011 3
b101010000111001111010 4
b11010 7
b11001 8

#296000
b101110110011 #
b1110110011110000 $
b11010 )
b101110110011 0
b1110110011110000 1

#300000
0!
0.

#305000
1!
b101001111100000000011 &
b101010100010010101101 '
b11000 *
r-5.414649963378906 ,
r-5.471725463867188 -
1.
b101001111100000000011 3
b101010100010010101101 4
b11010 7
b11001 8

#306000
b1100111000111000 #
b1110111110001100 $
b11011 )
b1100111000111000 0
b1110111110001100 1

#310000
0!
0.

#315000
1!
b101011001011111111001 &
b101011001010101011100 '
b11001 *
r-5.515602111816406 ,
r-5.365867614746094 -
1.
b101011001011111111001 3
b101011001010101011100 4
b11010 7
b11001 8

#316000
b1000011101010 #
b1111001001010001 $
b11100 )
b1000011101010 0
b1111001001010001 1

#320000
0!
0.

#325000
1!
b101011001100100101011 &
b101011111111110111010 '
b11010 *
r-5.203178405761719 ,
r-5.208282470703125 -
1.
b101011001100100101011 3
b101011111111110111010 4
b11010 7
b11001 8

#326000
b1101001111000001 #
b1111010100111000 $
b11101 )
b1101001111000001 0
b1111010100111000 1

#330000
0!
0.

#335000
1!
b101100110110001110110 &
b101101000001011000100 '
b11011 *
r-5.200843811035156 ,
r-5.000534057617188 -
1.
b101100110110001110110 3
b101101000001011000100 4
b11010 7
b11001 8

#336000
b1011010110101 #
b1111100000111001 $
b11110 )
b1011010110101 0
b1111100000111001 1

#340000
0!
0.

#345000
1!
b101101001111011110000 &
b101110001110100110101 '
b11100 *
r-4.788162231445312 ,
r-4.744598388671875 -
1.
b101101001111011110000 3
b101110001110100110101 4
b11010 7
b11001 8

#346000
b1101100111000001 #
b1111101101001101 $
b11111 )
b1101100111000001 0
b1111101101001101 1

#350000
0!
0.

#355000
1!
b101111010000011110110 &
b101111100110110000111 '
b11101 *
r-4.6895751953125 ,
r-4.442955017089844 -
1.
b101111010000011110110 3
b101111100110110000111 4
b11010 7
b11001 8

#356000
b1110011011101 #
b1111111001101110 $
b100000 )
b1110011011101 0
b1111111001101110 1

#360000
0!
0.

#365000
1!
b101111111111100101001 &
b110001001001000001110 '
b11110 *
r-4.185623168945312 ,
r-4.098579406738281 -
1.
b101111111111100101001 3
b110001001001000001110 4
b11010 7
b11001 8

#366000
b1101111111111111 #
b110010001 $
b100001 )
b1101111111111111 0
b110010001 1

#370000
0!
0.

#375000
1!
b110010010100110000111 &
b110010110100011100011 '
b11111 *
r-4.001640319824219 ,
r-3.714736938476562 -
1.
b110010010100110000111 3
b110010110100011100011 4
b11010 7
b11001 8

#376000
b10001100100010 #
b10010110010 $
b100010 )
b10001100100010 0
b10010110010 1

#380000
0!
0.

#385000
1!
b110011010110001001110 &
b110100100111111101111 '
b100000 *
r-3.418891906738281 ,
r-3.295143127441406 -
1.
b110011010110001001110 3
b110100100111111101111 4
b11010 7
b11001 8

#386000
b1110011000111110 #
b11111000110 $
b100011 )
b1110011000111110 0
b11111000110 1

#390000
0!
0.

#395000
1!
b110101111011100010110 &
b110110100010100000011 '
b100001 *
r-3.163467407226562 ,
r-2.843879699707031 -
1.
b110101111011100010110 3
b110110100010100000011 4
b11010 7
b11001 8

#396000
b10100101001010 #
b101011000111 $
b100100 )
b10100101001010 0
b101011000111 1

#400000
0!
0.

#405000
1!
b110111001010111011101 &
b111000100010111000000 '
b100010 *
r-2.517410278320312 ,
r-2.365211486816406 -
1.
b110111001010111011101 3
b111000100010111000000 4
b11010 7
b11001 8

#406000
b1110110000111110 #
b110110101110 $
b100101 )
b1110110000111110 0
b110110101110 1

#410000
0!
0.

#415000
1!
b111001111011111101101 &
b111010100111110100111 '
b100011 *
r-2.207298278808594 ,
r-1.86376953125 -
1.
b111001111011111101101 3
b111010100111110100111 4
b11010 7
b11001 8

#416000
b10111100010101 #
b1000001110011 $
b100110 )
b10111100010101 0
b1000001110011 1

#420000
0!
0.

#425000
1!
b111011010100100001010 &
b111100110000000110100 '
b100100 *
r-1.515769958496094 ,
r-1.344429016113281 -
1.
b111011010100100001010 3
b111100110000000110100 4
b11010 7
b11001 8

#426000
b1111000111000111 #
b1001100001111 $
b100111 )
b1111000111000111 0
b1001100001111 1

#430000
0!
0.

#435000
1!
b111110001100001011111 &
b111110111010011001010 '
b100101 *
r-1.169845581054688 ,
r-0.812103271484375 -
1.
b111110001100001011111 3
b111110111010011001010 4
b11010 7
b11001 8

#436000
b11010001001100 #
b1010101111101 $
b101000 )
b11010001001100 0
b1010101111101 1

#440000
0!
0.

#445000
1!
b111111101000110001000 &
b1000101010111001 '
b100110 *
r-0.4524002075195312 ,
r-0.2718963623046875 -
1.
b111111101000110001000 3
b1000101010111001 4
b11010 7
b11001 8

#446000
b1111011010100000 #
b1011110110101 $
b101001 )
b1111011010100000 0
b1011110110101 1

#450000
0!
0.

#455000
1!
b10100001110010100 &
b11001111101010100 '
b100111 *
r-0.09075927734375 ,
r0.2709426879882812 -
1.
b10100001110010100 3
b11001111101010100 4
b11010 7
b11001 8

#456000
b11100010111100 #
b1100110110011 $
b101010 )
b11100010111100 0
b1100110110011 1

#460000
0!
0.

#465000
1!
b11111101000010001 &
b101010111111101000 '
b101000 *
r0.631988525390625 ,
r0.811187744140625 -
1.
b11111101000010001 3
b101010111111101000 4
b11010 7
b11001 8

#466000
b1111101010011011 #
b1101101110010 $
b101011 )
b1111101010011011 0
b1101101110010 1

#470000
0!
0.

#475000
1!
b110110010000010110 &
b111011100111010111 '
b101001 *
r0.9884109497070312 ,
r1.34356689453125 -
1.
b110110010000010110 3
b111011100111010111 4
b11010 7
b11001 8

#476000
b11110000111000 #
b1110011101101 $
b101100 )
b11110000111000 0
b1110011101101 1

#480000
0!
0.

#485000
1!
b1000000110101001011 &
b1001011101010010011 '
b101010 *
r1.695480346679688 ,
r1.862968444824219 -
1.
b1000000110101001011 3
b1001011101010010011 4
b11010 7
b11001 8

#486000
b1111110110010000 #
b1111000100001 $
b101101 )
b1111110110010000 0
b1111000100001 1

#490000
0!
0.

#495000
1!
b1010110010011101111 &
b1011010111110100100 '
b101011 *
r2.025962829589844 ,
r2.364402770996094 -
1.
b1010110010011101111 3
b1011010111110100100 4
b11010 7
b11001 8

#496000
b11111010011111 #
b1111100001010 $
b101110 )
b11111010011111 0
b1111100001010 1

#500000
0!
0.

#505000
1!
b1011111011011010111 &
b1101001011010101110 '
b101100 *
r2.697135925292969 ,
r2.843048095703125 -
1.
b1011111011011010111 3
b1101001011010101110 4
b11010 7
b11001 8

#506000
b1111111101100010 #
b1111110100111 $
b101111 )
b1111111101100010 0
b1111110100111 1

#510000
0!
0.

#515000
1!
b1110011001001111101 &
b1110110110110000100 '
b101101 *
r2.982109069824219 ,
r3.294296264648438 -
1.
b1110011001001111101 3
b1110110110110000100 4
b11010 7
b11001 8

#516000
b11111111011000 #
b1111111110110 $
b110000 )
b11111111011000 0
b1111111110110 1

#520000
0!
0.

#525000
1!
b1111010001111111010 &
b10000011001000001110 '
b101110 *
r3.598609924316406 ,
r3.713897705078125 -
1.
b1111010001111111010 3
b10000011001000001110 4
b11010 7
b11001 8

#526000
b0 #
b110001 )
b0 0

#530000
0!
0.

#535000
1!
b10001011101100001110 &
b10001110001001011110 '
b101111 *
r3.820266723632812 ,
r4.097763061523438 -
1.
b10001011101100001110 3
b10001110001001011110 4
b11010 7
b11001 8

#536000
b11111111011000 #
b1111110100111 $
b110010 )
b11111111011000 0
b1111110100111 1

#540000
0!
0.

#545000
1!
b10010000010000110010 &
b10010111110011001100 '
b110000 *
r4.365341186523438 ,
r4.442123413085938 -
1.
b10010000010000110010 3
b10010111110011001100 4
b11010 7
b11001 8

#546000
b1111111101100010 #
b1111100001010 $
b110011 )
b1111111101100010 0
b1111100001010 1

#550000
0!
0.

#555000
1!
b10011110111110001011 &
b10011111111111010111 '
b110001 *
r4.508193969726562 ,
r4.743743896484375 -
1.
b10011110111110001011 3
b10011111111111010111 4
b11010 7
b11001 8

#556000
b11111010011111 #
b1111000100001 $
b110100 )
b11111010011111 0
b1111000100001 1

#560000
0!
0.

#565000
1!
b10100000100111110100 &
b10100110101000111000 '
b110010 *
r4.967857360839844 ,
r4.999687194824219 -
1.
b10100000100111110100 3
b10100110101000111000 4
b11010 7
b11001 8

#566000
b1111110110010000 #
b1110011101101 $
b110101 )
b1111110110010000 0
b1110011101101 1

#570000
0!
0.

#575000
1!
b10101100010000001100 &
b10101011101011101001 '
b110011 *
r5.019439697265625 ,
r5.20745849609375 -
1.
b10101100010000001100 3
b10101011101011101001 4
b11010 7
b11001 8

#576000
b11110000111000 #
b1101101110010 $
b110110 )
b11110000111000 0
b1101101110010 1

#580000
0!
0.

#585000
1!
b10101010101100101001 &
b10101111000100100010 '
b110100 *
r5.382904052734375 ,
r5.365058898925781 -
1.
b10101010101100101001 3
b10101111000100100010 4
b11010 7
b11001 8

#586000
b1111101010011011 #
b1100110110011 $
b110111 )
b1111101010011011 0
b1100110110011 1

#590000
0!
0.

#595000
1!
b10110011000001100010 &
b10110000110001100000 '
b110101 *
r5.334297180175781 ,
r5.470962524414062 -
1.
b10110011000001100010 3
b10110000110001100000 4
b11010 7
b11001 8

#596000
b11100010111100 #
b1011110110101 $
b111000 )
b11100010111100 0
b1011110110101 1

#600000
0!
0.

#605000
1!
b10101110000110010010 &
b110110 *
r5.594497680664062 ,
r5.524169921875 -
1.
b10101110000110010010 3
b11010 7
b11001 8

#606000
b1111011010100000 #
b1010101111101 $
b111001 )
b1111011010100000 0
b1010101111101 1

#610000
0!
0.

#615000
1!
b10110011000001100010 &
b10101111000100100010 '
b110111 *
r5.440567016601562 ,
1.
b10110011000001100010 3
b10101111000100100010 4
b11010 7
b11001 8

#616000
b11010001001100 #
b1001100001111 $
b111010 )
b11010001001100 0
b1001100001111 1

#620000
0!
0.

#625000
1!
b10101010101100101001 &
b10101011101011101001 '
b111000 *
r5.594497680664062 ,
r5.470962524414062 -
1.
b10101010101100101001 3
b10101011101011101001 4
b11010 7
b11001 8

#626000
b1111000111000111 #
b1000001110011 $
b111011 )
b1111000111000111 0
b1000001110011 1

#630000
0!
0.

#635000
1!
b10101100010000001100 &
b10100110101000111000 '
b111001 *
r5.334297180175781 ,
r5.365058898925781 -
1.
b10101100010000001100 3
b10100110101000111000 4
b11010 7
b11001 8

#636000
b10111100010101 #
b110110101110 $
b111100 )
b10111100010101 0
b110110101110 1

#640000
0!
0.

#645000
1!
b10100000100111110100 &
b10011111111111010111 '
b111010 *
r5.382904052734375 ,
r5.20745849609375 -
1.
b10100000100111110100 3
b10011111111111010111 4
b11010 7
b11001 8

#646000
b1110110000111110 #
b101011000111 $
b111101 )
b1110110000111110 0
b101011000111 1

#650000
0!
0.

#655000
1!
b10011110111110001011 &
b10010111110011001100 '
b111011 *
r5.019439697265625 ,
r4.999687194824219 -
1.
b10011110111110001011 3
b10010111110011001100 4
b11010 7
b11001 8

#656000
b10100101001010 #
b11111000110 $
b111110 )
b10100101001010 0
b11111000110 1

#660000
0!
0.

#665000
1!
b10010000010000110010 &
b10001110001001011110 '
b111100 *
r4.967857360839844 ,
r4.743743896484375 -
1.
b10010000010000110010 3
b10001110001001011110 4
b11010 7
b11001 8

#666000
b1110011000111110 #
b10010110010 $
b111111 )
b1110011000111110 0
b10010110010 1

#670000
0!
0.

#675000
1!
b10001011101100001110 &
b10000011001000001110 '
b111101 *
r4.508193969726562 ,
r4.442123413085938 -
1.
b10001011101100001110 3
b10000011001000001110 4
b11010 7
b11001 8

#676000
b10001100100010 #
b110010001 $
b1000000 )
b10001100100010 0
b110010001 1

#680000
0!
0.

